odoo10_addon_project_parent-10.0.1.0.0-py2.7-nspkg.pth
odoo/addons/project_parent/README.rst
odoo/addons/project_parent/__init__.py
odoo/addons/project_parent/__manifest__.py
odoo/addons/project_parent/models/__init__.py
odoo/addons/project_parent/models/account_analytic_account.py
odoo/addons/project_parent/static/description/icon.png
odoo/addons/project_parent/views/project_parent.xml
odoo10_addon_project_parent-10.0.1.0.0.dist-info/DESCRIPTION.rst
odoo10_addon_project_parent-10.0.1.0.0.dist-info/METADATA
odoo10_addon_project_parent-10.0.1.0.0.dist-info/RECORD
odoo10_addon_project_parent-10.0.1.0.0.dist-info/WHEEL
odoo10_addon_project_parent-10.0.1.0.0.dist-info/metadata.json
odoo10_addon_project_parent-10.0.1.0.0.dist-info/namespace_packages.txt
odoo10_addon_project_parent-10.0.1.0.0.dist-info/top_level.txt
